exonum_client_cis/__init__.py
exonum_client_cis/api.py
exonum_client_cis/client.py
exonum_client_cis/crypto.py
exonum_client_cis/message.py
exonum_client_cis/module_manager.py
exonum_client_cis/protobuf_loader.py
exonum_client_cis/protoc.py
exonum_client_cis/proofs/__init__.py
exonum_client_cis/proofs/encoder.py
exonum_client_cis/proofs/hasher.py
exonum_client_cis/proofs/utils.py
exonum_client_cis/proofs/list_proof/__init__.py
exonum_client_cis/proofs/list_proof/errors.py
exonum_client_cis/proofs/list_proof/key.py
exonum_client_cis/proofs/list_proof/list_proof.py
exonum_client_cis/proofs/map_proof/__init__.py
exonum_client_cis/proofs/map_proof/branch_node.py
exonum_client_cis/proofs/map_proof/constants.py
exonum_client_cis/proofs/map_proof/errors.py
exonum_client_cis/proofs/map_proof/map_proof.py
exonum_client_cis/proofs/map_proof/map_proof_builder.py
exonum_client_cis/proofs/map_proof/optional_entry.py
exonum_client_cis/proofs/map_proof/proof_path.py
exonum_client_cis-0.4.0.dev6.dist-info/LICENSE
exonum_client_cis-0.4.0.dev6.dist-info/METADATA
exonum_client_cis-0.4.0.dev6.dist-info/WHEEL
exonum_client_cis-0.4.0.dev6.dist-info/top_level.txt
exonum_client_cis-0.4.0.dev6.dist-info/RECORD
