Metadata-Version: 2.1
Name: exonum-client-cis
Version: 0.4.0.dev6
Summary: Exonum CIS Python Light Client
Home-page: UNKNOWN
Author: The Exonum team
Author-email: contact@exonum.com
License: UNKNOWN
Platform: UNKNOWN
Classifier: Programming Language :: Python :: 3
Classifier: License :: OSI Approved :: Apache Software License
Classifier: Operating System :: OS Independent
Classifier: Topic :: Security :: Cryptography
Requires-Python: >=3.4
Requires-Dist: protobuf
Requires-Dist: pysodium
Requires-Dist: requests
Requires-Dist: websocket-client-py3
